watchmen_rest_doll/__init__.py
watchmen_rest_doll/admin/__init__.py
watchmen_rest_doll/admin/enumeration_router.py
watchmen_rest_doll/admin/pipeline_graphic_router.py
watchmen_rest_doll/admin/pipeline_router.py
watchmen_rest_doll/admin/space_router.py
watchmen_rest_doll/admin/synonym_topic_router.py
watchmen_rest_doll/admin/topic_router.py
watchmen_rest_doll/admin/topic_snapshot_scheduler_router.py
watchmen_rest_doll/admin/user_group_router.py
watchmen_rest_doll/admin/user_router.py
watchmen_rest_doll/analysis/__init__.py
watchmen_rest_doll/analysis/pipeline_index_router.py
watchmen_rest_doll/analysis/topic_index_router.py
watchmen_rest_doll/auth/__init__.py
watchmen_rest_doll/auth/authenticate_router.py
watchmen_rest_doll/console/__init__.py
watchmen_rest_doll/console/connected_space_graphic_router.py
watchmen_rest_doll/console/connected_space_router.py
watchmen_rest_doll/console/dashboard_router.py
watchmen_rest_doll/console/report_router.py
watchmen_rest_doll/console/subject_router.py
watchmen_rest_doll/doll.py
watchmen_rest_doll/gui/__init__.py
watchmen_rest_doll/gui/favorite_router.py
watchmen_rest_doll/gui/last_snapshot_router.py
watchmen_rest_doll/ingest/__init__.py
watchmen_rest_doll/ingest/config_router.py
watchmen_rest_doll/ingest/monitor_router.py
watchmen_rest_doll/main.py
watchmen_rest_doll/meta_import/__init__.py
watchmen_rest_doll/meta_import/connected_space_import_router.py
watchmen_rest_doll/meta_import/dashboard_import_router.py
watchmen_rest_doll/meta_import/mix_import_router.py
watchmen_rest_doll/meta_import/pipeline_import_router.py
watchmen_rest_doll/meta_import/report_import_router.py
watchmen_rest_doll/meta_import/space_import_router.py
watchmen_rest_doll/meta_import/subject_import_router.py
watchmen_rest_doll/meta_import/topic_import_router.py
watchmen_rest_doll/meta_import/user_group_import_router.py
watchmen_rest_doll/meta_import/user_import_router.py
watchmen_rest_doll/meta_import/validator.py
watchmen_rest_doll/settings.py
watchmen_rest_doll-18.0.1.dist-info/METADATA
watchmen_rest_doll-18.0.1.dist-info/WHEEL
watchmen_rest_doll-18.0.1.dist-info/licenses/LICENSE
watchmen_rest_doll-18.0.1.dist-info/RECORD
